facecroppy/__init__.py
facecroppy/facecroppy.py
facecroppy-0.2.0.dist-info/LICENSE
facecroppy-0.2.0.dist-info/METADATA
facecroppy-0.2.0.dist-info/WHEEL
facecroppy-0.2.0.dist-info/top_level.txt
facecroppy-0.2.0.dist-info/RECORD
