Metadata-Version: 2.1
Name: facecroppy
Version: 0.2.0
Summary: Smart face cropping tool for image processing
Author-email: BIFF <info@biff.ai>
License: MIT License
Project-URL: Homepage, https://biff.ai/bif-0001
Keywords: facecropping,tool,ai
Classifier: License :: OSI Approved :: MIT License
Classifier: Programming Language :: Python
Classifier: Programming Language :: Python :: 3
Requires-Python: >=3.7
License-File: LICENSE
Requires-Dist: mtcnn (>=0.1.1)
Requires-Dist: opencv-python (>=4.1.0)
Requires-Dist: tensorflow (>=2.11.0)
